portfolioscience/__init__.py
portfolioscience/riskapi_enterprise.pyd
portfolioscience/riskapi_enterprise.so
portfolioscience-1.0.15.dist-info/licenses/LICENSE
portfolioscience-1.0.15.dist-info/METADATA
portfolioscience-1.0.15.dist-info/WHEEL
portfolioscience-1.0.15.dist-info/top_level.txt
portfolioscience-1.0.15.dist-info/RECORD
