Metadata-Version: 2.4
Name: portfolioscience
Version: 1.0.15
Summary: PortfolioScience RiskAPI Enterprise Client
Home-page: https://www.portfolioscience.com/products/riskapi-enterprise
Author: Portfolio Science, Inc.
Author-email: sales@portfolioscience.com
Classifier: Programming Language :: Python :: 3
Classifier: Operating System :: Microsoft :: Windows
Classifier: Operating System :: POSIX :: Linux
Classifier: License :: Other/Proprietary License
Requires-Python: >=3.13
License-File: LICENSE
Requires-Dist: Cython
Requires-Dist: pycryptodome
Requires-Dist: python-dateutil
Dynamic: author
Dynamic: author-email
Dynamic: classifier
Dynamic: description
Dynamic: home-page
Dynamic: license-file
Dynamic: requires-dist
Dynamic: requires-python
Dynamic: summary
